setup.py
alibabacloud_ha3_util/__init__.py
alibabacloud_ha3_util/client.py
alibabacloud_ha3_util.egg-info/PKG-INFO
alibabacloud_ha3_util.egg-info/SOURCES.txt
alibabacloud_ha3_util.egg-info/dependency_links.txt
alibabacloud_ha3_util.egg-info/top_level.txt